lightningnbeats/__init__.py
lightningnbeats/constants.py
lightningnbeats/loaders.py
lightningnbeats/losses.py
lightningnbeats/models.py
lightningnbeats/blocks/__init__.py
lightningnbeats/blocks/blocks.py
lightningnbeats/data/Electric_Production.csv
lightningnbeats/data/__init__.py
lightningnbeats/data/daily-minimum-temperatures-in-me.csv
lightningnbeats/data/energy_dataset.csv
lightningnbeats/data/milk.csv
lightningnbeats/data/monthly-beer-production-in-austr.csv
lightningnbeats/data/monthly-sunspots.csv
lightningnbeats/data/sales-of-shampoo-over-a-three-ye.csv
lightningnbeats/data/M4/M4-info.csv
lightningnbeats/data/M4/__init__.py
lightningnbeats/data/M4/m4dataset.py
lightningnbeats/data/M4/Test/Daily-test.csv
lightningnbeats/data/M4/Test/Hourly-test.csv
lightningnbeats/data/M4/Test/Monthly-test.csv
lightningnbeats/data/M4/Test/Quarterly-test.csv
lightningnbeats/data/M4/Test/Weekly-test.csv
lightningnbeats/data/M4/Test/Yearly-test.csv
lightningnbeats/data/M4/Train/Daily-train.csv
lightningnbeats/data/M4/Train/Hourly-train.csv
lightningnbeats/data/M4/Train/Monthly-train.csv
lightningnbeats/data/M4/Train/Quarterly-train.csv
lightningnbeats/data/M4/Train/Weekly-train.csv
lightningnbeats/data/M4/Train/Yearly-train.csv
lightningnbeats/data/M4/docs/M4CompetitorsGuide.pdf
lightningnbeats/data/tourism1/example.csv
lightningnbeats/data/tourism1/template.csv
lightningnbeats/data/tourism1/tourism_data.csv
lightningnbeats/data/tourism2/example_submission.csv
lightningnbeats/data/tourism2/tourism2_revision2.csv
lightningnbeats-0.1.1.dist-info/LICENSE
lightningnbeats-0.1.1.dist-info/METADATA
lightningnbeats-0.1.1.dist-info/WHEEL
lightningnbeats-0.1.1.dist-info/top_level.txt
lightningnbeats-0.1.1.dist-info/RECORD
