Metadata-Version: 2.1
Name: lightningnbeats
Version: 0.1.1
Summary: A Pytorch Lightning implementation of the N-BEATS algorithm with some extended functionality.
Author-email: Daniel Byrne <realdanielbyrne@icloud.com>
Project-URL: Homepage, https://github.com/realdanielbyrne/N-BEATS-Lightning
Classifier: Intended Audience :: Science/Research
Classifier: Intended Audience :: Developers
Classifier: Programming Language :: Python
Classifier: Topic :: Software Development
Classifier: Topic :: Scientific/Engineering
Classifier: Operating System :: OS Independent
Classifier: Programming Language :: Python :: 3
Requires-Python: >=3.9.0
License-File: LICENSE
Requires-Dist: lightning
Requires-Dist: matplotlib
Requires-Dist: numpy
Requires-Dist: pandas
Requires-Dist: pytorch-lightning
Requires-Dist: PyWavelets
Requires-Dist: scipy
Requires-Dist: seaborn
Requires-Dist: tensorboard
Requires-Dist: torch
Requires-Dist: tqdm
Requires-Dist: ipykernel
Requires-Dist: ipython
Requires-Dist: statsmodels
